specific/__init__.py
specific/__main__.py
specific/cli.py
specific/exceptions.py
specific/handlers.py
specific/http_facts.py
specific/json_schema.py
specific/lifecycle.py
specific/mock.py
specific/options.py
specific/problem.py
specific/resolver.py
specific/spec.py
specific/utils.py
specific/apis/__init__.py
specific/apis/abstract.py
specific/apis/flask_api.py
specific/apis/flask_utils.py
specific/apps/__init__.py
specific/apps/abstract.py
specific/apps/flask_app.py
specific/decorators/__init__.py
specific/decorators/decorator.py
specific/decorators/metrics.py
specific/decorators/parameter.py
specific/decorators/produces.py
specific/decorators/response.py
specific/decorators/security.py
specific/decorators/uri_parsing.py
specific/decorators/validation.py
specific/operations/__init__.py
specific/operations/abstract.py
specific/operations/compat.py
specific/operations/openapi.py
specific/operations/secure.py
specific/operations/swagger2.py
specific-0.0.1.dist-info/LICENSE.txt
specific-0.0.1.dist-info/METADATA
specific-0.0.1.dist-info/WHEEL
specific-0.0.1.dist-info/entry_points.txt
specific-0.0.1.dist-info/top_level.txt
specific-0.0.1.dist-info/RECORD
