Metadata-Version: 2.1
Name: specific
Version: 0.0.1
Summary: Specific - spec-first web framework
Home-page: https://github.com/dtkav/specific
Author: Daniel Grossmann-Kavanagh
License: Apache License Version 2.0
Keywords: openapi oai rest api oauth flask microservice framework
Platform: UNKNOWN
Classifier: Programming Language :: Python
Classifier: Programming Language :: Python :: 2.7
Classifier: Programming Language :: Python :: 3.4
Classifier: Programming Language :: Python :: 3.5
Classifier: Programming Language :: Python :: 3.6
Classifier: Programming Language :: Python :: 3.7
Classifier: Development Status :: 5 - Production/Stable
Classifier: Intended Audience :: Developers
Classifier: Operating System :: OS Independent
Classifier: Topic :: Internet :: WWW/HTTP :: WSGI :: Application
Classifier: Topic :: Software Development :: Libraries :: Application Frameworks
Requires-Dist: clickclick (>=1.2)
Requires-Dist: jsonschema (<3.0.0,>=2.5.1)
Requires-Dist: PyYAML (>=3.13)
Requires-Dist: requests (>=2.9.1)
Requires-Dist: six (>=1.9)
Requires-Dist: inflection (>=0.3.1)
Requires-Dist: openapi-spec-validator (>=0.2.4)
Requires-Dist: flask (>=0.10.1)
Requires-Dist: swagger-ui-bundle (>=0.0.2)
Requires-Dist: pathlib (>=1.0.1) ; python_version < "3.4"
Requires-Dist: typing (>=3.6.1) ; python_version < "3.6"
Provides-Extra: tests
Requires-Dist: decorator ; extra == 'tests'
Requires-Dist: mock ; extra == 'tests'
Requires-Dist: pytest ; extra == 'tests'
Requires-Dist: pytest-cov ; extra == 'tests'
Requires-Dist: testfixtures ; extra == 'tests'
